schurtransform/__init__.py
schurtransform/character_table.py
schurtransform/log_formats.py
schurtransform/parsing_gap_output.py
schurtransform/plotting.py
schurtransform/schur_transform.py
schurtransform/tensor.py
schurtransform/tensor_operator.py
schurtransform/version.txt
schurtransform/character_tables/__init__.py
schurtransform/character_tables/s2.csv
schurtransform/character_tables/s3.csv
schurtransform/character_tables/s4.csv
schurtransform/character_tables/s5.csv
schurtransform/character_tables/s6.csv
schurtransform/character_tables/symmetric_group_conjugacy_classes.csv
schurtransform/examples/__init__.py
schurtransform/lung_data/__init__.py
schurtransform/lung_data/case1_4D-75_T00.txt
schurtransform/lung_data/case1_4D-75_T10.txt
schurtransform/lung_data/case1_4D-75_T20.txt
schurtransform/lung_data/case1_4D-75_T30.txt
schurtransform/lung_data/case1_4D-75_T40.txt
schurtransform/lung_data/case1_4D-75_T50.txt
schurtransform/lung_data/case2_4D-75_T00.txt
schurtransform/lung_data/case2_4D-75_T10.txt
schurtransform/lung_data/case2_4D-75_T20.txt
schurtransform/lung_data/case2_4D-75_T30.txt
schurtransform/lung_data/case2_4D-75_T40.txt
schurtransform/lung_data/case2_4D-75_T50.txt
schurtransform/lung_data/case3_4D-75_T00.txt
schurtransform/lung_data/case3_4D-75_T10.txt
schurtransform/lung_data/case3_4D-75_T20.txt
schurtransform/lung_data/case3_4D-75_T30.txt
schurtransform/lung_data/case3_4D-75_T40.txt
schurtransform/lung_data/case3_4D-75_T50.txt
schurtransform/lung_data/case4_4D-75_T00.txt
schurtransform/lung_data/case4_4D-75_T10.txt
schurtransform/lung_data/case4_4D-75_T20.txt
schurtransform/lung_data/case4_4D-75_T30.txt
schurtransform/lung_data/case4_4D-75_T40.txt
schurtransform/lung_data/case4_4D-75_T50.txt
schurtransform/lung_data/case5_4D-75_T00.txt
schurtransform/lung_data/case5_4D-75_T10.txt
schurtransform/lung_data/case5_4D-75_T20.txt
schurtransform/lung_data/case5_4D-75_T30.txt
schurtransform/lung_data/case5_4D-75_T40.txt
schurtransform-0.3.5.dist-info/LICENSE
schurtransform-0.3.5.dist-info/METADATA
schurtransform-0.3.5.dist-info/WHEEL
schurtransform-0.3.5.dist-info/top_level.txt
schurtransform-0.3.5.dist-info/RECORD
