Metadata-Version: 2.1
Name: schurtransform
Version: 0.3.5
Summary: The Fourier-Schur transform for spatial statistics.
Home-page: https://github.com/schur-transform/schurtransform
Author: James Mathews
Author-email: mathewj2@mskcc.org
Project-URL: Documentation, https://schurtransform.readthedocs.io/en/stable/readme.html
Project-URL: Source code, https://github.com/schur-transform/schurtransform
Classifier: Programming Language :: Python :: 3
Classifier: License :: OSI Approved :: GNU General Public License v3 (GPLv3)
Classifier: Topic :: Scientific/Engineering
Classifier: Intended Audience :: Science/Research
Requires-Python: >=3.8
License-File: LICENSE
Requires-Dist: numpy (==1.22.3)
Requires-Dist: pandas (==1.1.5)
Requires-Dist: matplotlib (==3.4.2)
Requires-Dist: seaborn (==0.11.1)
